yog/__init__.py
yog/command.py
yog/git_utils.py
yog/logging_utils.py
yog/model_utils.py
yog/ssh_utils.py
yog/host/__init__.py
yog/host/compose.py
yog/host/docker_attrs.py
yog/host/main.py
yog/host/manage.py
yog/host/necronomicon.py
yog/host/os_utils.py
yog/host/pipx.py
yog/host/pki.py
yog/host/pki_model.py
yog/host/systemd.py
yog/host/test_docker_attrs.py
yog/host/test_necronomicon.py
yog/host/test_pipx.py
yog/host/utils.py
yog/repo/__init__.py
yog/repo/main.py
yog/res/__init__.py
yog/res/cas.yml
yog/res/docker_test.yml
yog/res/sample_necronomicon.yml
yog/res/sample_needs_tunnel_back.yml
yog/res/sample_pki_necronomicon.yml
yog/res/sample_site_necronomicon.yml
yog-2.4.0.dist-info/METADATA
yog-2.4.0.dist-info/WHEEL
yog-2.4.0.dist-info/entry_points.txt
yog-2.4.0.dist-info/licenses/COPYING
yog-2.4.0.dist-info/RECORD
