Metadata-Version: 2.4
Name: yog
Version: 2.4.0
Summary: The Gate and Key
Author-email: Josh Hertlein <jmhertlein@gmail.com>
License-Expression: AGPL-3.0-or-later
License-File: COPYING
Requires-Python: ~=3.13.0
Requires-Dist: docker<8,>=7.1.0
Requires-Dist: paramiko<4,>=3.5.1
Requires-Dist: pyyaml~=6.0
Requires-Dist: requests==2.31.0
